{"request_hash": "request:anime:c4ebd3ff740b3de41fcf76fe4010045bdd24c071", "request_cached": true, "request_cache_expiry": 71619, "mal_id": 22593, "url": "https://myanimelist.net/anime/22593/Potecco_Babies_2011", "image_url": "https://cdn.myanimelist.net/images/anime/7/58921.jpg", "trailer_url": null, "title": "Potecco Babies (2011)", "title_english": null, "title_japanese": "\u30dd\u30c6\u30c3\u30b3\u30d9\u30a4\u30d3\u30fc\u30ba(2011)", "title_synonyms": [], "type": "ONA", "source": "Unknown", "episodes": 12, "status": "Finished Airing", "airing": false, "aired": {"from": "2011-04-22T00:00:00+00:00", "to": "2011-07-10T00:00:00+00:00", "prop": {"from": {"day": 22, "month": 4, "year": 2011}, "to": {"day": 10, "month": 7, "year": 2011}}, "string": "Apr 22, 2011 to Jul 10, 2011"}, "duration": "1 min per ep", "rating": "G - All Ages", "score": null, "scored_by": null, "rank": 11523, "popularity": 13821, "members": 266, "favorites": 0, "synopsis": "Anime about potato characters continues.", "background": null, "premiered": null, "broadcast": null, "related": {"Prequel": [{"mal_id": 8958, "type": "anime", "name": "Potecco Babies", "url": "https://myanimelist.net/anime/8958/Potecco_Babies"}]}, "producers": [], "licensors": [], "studios": [{"mal_id": 247, "type": "anime", "name": "Shin-Ei Animation", "url": "https://myanimelist.net/anime/producer/247/Shin-Ei_Animation"}], "genres": [{"mal_id": 4, "type": "anime", "name": "Comedy", "url": "https://myanimelist.net/anime/genre/4/Comedy"}], "opening_themes": [], "ending_themes": []}