{"request_hash": "request:anime:e40cc7fc4ce36e708c6944f8927709f847723957", "request_cached": true, "request_cache_expiry": 86400, "mal_id": 32437, "url": "https://myanimelist.net/anime/32437/One_Piece__Long_Ring_Long_Land-hen", "image_url": "https://cdn.myanimelist.net/images/anime/12/83503.jpg", "trailer_url": null, "title": "One Piece: Long Ring Long Land-hen", "title_english": null, "title_japanese": "\u30ef\u30f3\u30d4\u30fc\u30b9\uff5e\u30ed\u30f3\u30b0\u30ea\u30f3\u30b0\u30ed\u30f3\u30b0\u30e9\u30f3\u30c9\u7de8\uff5e \u4e00\u591c\u9650\u308a\u306e\u7279\u5225\u7de8\u96c6\u7248", "title_synonyms": ["One Piece: Long Ring Long Land Arc - A One Night Abridged Special", "Episode of Foxy", "One Piece: Long Ring Long Land-hen - Ichiya Kagiri no Tokubetsu Henshuu-ban"], "type": "Special", "source": "Manga", "episodes": 1, "status": "Finished Airing", "airing": false, "aired": {"from": "2015-12-11T00:00:00+00:00", "to": null, "prop": {"from": {"day": 11, "month": 12, "year": 2015}, "to": {"day": null, "month": null, "year": null}}, "string": "Dec 11, 2015"}, "duration": "1 hr 15 min", "rating": "PG-13 - Teens 13 or older", "score": 6.75, "scored_by": 1786, "rank": 4659, "popularity": 5689, "members": 6818, "favorites": 15, "synopsis": "A 75-minute recap of episodes 207-219, the Long Ring Long Land Arc.", "background": null, "premiered": null, "broadcast": null, "related": {"Full story": [{"mal_id": 21, "type": "anime", "name": "One Piece", "url": "https://myanimelist.net/anime/21/One_Piece"}]}, "producers": [{"mal_id": 169, "type": "anime", "name": "Fuji TV", "url": "https://myanimelist.net/anime/producer/169/Fuji_TV"}], "licensors": [], "studios": [{"mal_id": 18, "type": "anime", "name": "Toei Animation", "url": "https://myanimelist.net/anime/producer/18/Toei_Animation"}], "genres": [{"mal_id": 1, "type": "anime", "name": "Action", "url": "https://myanimelist.net/anime/genre/1/Action"}, {"mal_id": 2, "type": "anime", "name": "Adventure", "url": "https://myanimelist.net/anime/genre/2/Adventure"}, {"mal_id": 4, "type": "anime", "name": "Comedy", "url": "https://myanimelist.net/anime/genre/4/Comedy"}, {"mal_id": 31, "type": "anime", "name": "Super Power", "url": "https://myanimelist.net/anime/genre/31/Super_Power"}, {"mal_id": 8, "type": "anime", "name": "Drama", "url": "https://myanimelist.net/anime/genre/8/Drama"}, {"mal_id": 10, "type": "anime", "name": "Fantasy", "url": "https://myanimelist.net/anime/genre/10/Fantasy"}, {"mal_id": 27, "type": "anime", "name": "Shounen", "url": "https://myanimelist.net/anime/genre/27/Shounen"}], "opening_themes": [], "ending_themes": []}