{"request_hash": "request:anime:58230fe6a13599985bf5b0def442e9c3a95eabf4", "request_cached": true, "request_cache_expiry": 38561, "mal_id": 9008, "url": "https://myanimelist.net/anime/9008/Netorare_Fighter_Yaricchingu", "image_url": "https://cdn.myanimelist.net/images/anime/11/24924.jpg", "trailer_url": null, "title": "Netorare Fighter Yaricchingu!", "title_english": null, "title_japanese": "\u5bdd\u53d6\u3089\u308c\u30d5\u30a1\u30a4\u30bf\u30fc \u30e4\u30ea\u3063\u3061\u3093\u3050!", "title_synonyms": [], "type": "OVA", "source": "Original", "episodes": 3, "status": "Finished Airing", "airing": false, "aired": {"from": "2010-07-16T00:00:00+00:00", "to": "2011-02-18T00:00:00+00:00", "prop": {"from": {"day": 16, "month": 7, "year": 2010}, "to": {"day": 18, "month": 2, "year": 2011}}, "string": "Jul 16, 2010 to Feb 18, 2011"}, "duration": "21 min per ep", "rating": "Rx - Hentai", "score": 6.31, "scored_by": 1424, "rank": null, "popularity": 6844, "members": 4274, "favorites": 30, "synopsis": "Ai has been captured and is held hostage at a luxury ship, Harry goes to her rescue but when he arrives he witnesses Ai's humiliation at the hands of Onizaki and his goons. Harry and his friends cant do anything but witness Ai being sexually abused, what's worst Ai will be the main attraction in the ships \"special ring\"...", "background": null, "premiered": null, "broadcast": null, "related": {}, "producers": [{"mal_id": 405, "type": "anime", "name": "T-Rex", "url": "https://myanimelist.net/anime/producer/405/T-Rex"}, {"mal_id": 981, "type": "anime", "name": "BOOTLEG", "url": "https://myanimelist.net/anime/producer/981/BOOTLEG"}], "licensors": [], "studios": [], "genres": [{"mal_id": 12, "type": "anime", "name": "Hentai", "url": "https://myanimelist.net/anime/genre/12/Hentai"}], "opening_themes": [], "ending_themes": []}