{"request_hash": "request:anime:f7d6de54f51e63af267aad7459657436aca8c6d2", "request_cached": true, "request_cache_expiry": 84275, "mal_id": 41458, "url": "https://myanimelist.net/anime/41458/Origami_Ninja_Koyankinte", "image_url": "https://cdn.myanimelist.net/images/anime/1860/106477.jpg", "trailer_url": null, "title": "Origami Ninja Koyankinte", "title_english": null, "title_japanese": "\u304a\u308a\u304c\u307f\u306b\u3093\u3058\u3083 \u30b3\u30fc\u30e4\u30f3\uff20\u304d\u3093\u3066\u308c", "title_synonyms": ["Happy Smile \u2661 Dream"], "type": "TV", "source": "Unknown", "episodes": null, "status": "Currently Airing", "airing": true, "aired": {"from": "2020-04-07T00:00:00+00:00", "to": null, "prop": {"from": {"day": 7, "month": 4, "year": 2020}, "to": {"day": null, "month": null, "year": null}}, "string": "Apr 7, 2020 to ?"}, "duration": "Unknown", "rating": "PG - Children", "score": null, "scored_by": null, "rank": 11298, "popularity": 17055, "members": 74, "favorites": 0, "synopsis": "Koyan, the Origami Ninja, came to Earth from his planet Origamio to find the magical stone \"Hapiton\" that has the ability to make people happy. On the way, he was joined by childhood friend Namin anda new friend Lublin. One day, a villain called Evilrun appeared. Evilrun has a black hole in her stomach and tries to inhale anything. Every time an event happens, Evilrun gets in the way of Koyan and friends. But what Evilrun's aim is remains a mystery...", "background": null, "premiered": "Spring 2020", "broadcast": "Tuesdays at 07:30 (JST)", "related": {}, "producers": [{"mal_id": 16, "type": "anime", "name": "TV Tokyo", "url": "https://myanimelist.net/anime/producer/16/TV_Tokyo"}], "licensors": [], "studios": [{"mal_id": 324, "type": "anime", "name": "Directions", "url": "https://myanimelist.net/anime/producer/324/Directions"}], "genres": [{"mal_id": 4, "type": "anime", "name": "Comedy", "url": "https://myanimelist.net/anime/genre/4/Comedy"}, {"mal_id": 15, "type": "anime", "name": "Kids", "url": "https://myanimelist.net/anime/genre/15/Kids"}], "opening_themes": [], "ending_themes": []}