{"request_hash": "request:anime:4ec43f0786b1762ca3bb9585dbf2927f5bf843f2", "request_cached": true, "request_cache_expiry": 15358, "mal_id": 38733, "url": "https://myanimelist.net/anime/38733/Hataraku_Saibou__Kaze_Shoukougun", "image_url": "https://cdn.myanimelist.net/images/anime/1888/96676.jpg", "trailer_url": "https://www.youtube.com/embed/mm05YU6ZKeE?enablejsapi=1&wmode=opaque&autoplay=1", "title": "Hataraku Saibou: Kaze Shoukougun", "title_english": "Cells at Work Special", "title_japanese": "\u306f\u305f\u3089\u304f\u7d30\u80de \u65b0\u4f5c\u30a8\u30d4\u30bd\u30fc\u30c9\u300c\u98a8\u90aa\u75c7\u5019\u7fa4\u300d", "title_synonyms": ["Hataraku Saibou Special", "Hataraku Saibou: Cold Syndrome"], "type": "Special", "source": "Manga", "episodes": 1, "status": "Finished Airing", "airing": false, "aired": {"from": "2018-12-27T00:00:00+00:00", "to": null, "prop": {"from": {"day": 27, "month": 12, "year": 2018}, "to": {"day": null, "month": null, "year": null}}, "string": "Dec 27, 2018"}, "duration": "23 min", "rating": "PG-13 - Teens 13 or older", "score": 7.29, "scored_by": 19876, "rank": 2413, "popularity": 2759, "members": 33704, "favorites": 5, "synopsis": "A mysterious cell wearing a stylish hat appears before the regular cells, who are bored with just the same (cell division) work over and over again, every day. This mysterious cell lures the regular cells into a mischievous scheme against White Blood Cell and Killer T Cell. The regular cells enjoy working out their everyday, pent-up frustration. But, just who exactly is this cell wearing a stylish hat? (Source: ANN)", "background": null, "premiered": null, "broadcast": null, "related": {"Parent story": [{"mal_id": 37141, "type": "anime", "name": "Hataraku Saibou (TV)", "url": "https://myanimelist.net/anime/37141/Hataraku_Saibou_TV"}]}, "producers": [], "licensors": [], "studios": [{"mal_id": 287, "type": "anime", "name": "David Production", "url": "https://myanimelist.net/anime/producer/287/David_Production"}], "genres": [{"mal_id": 4, "type": "anime", "name": "Comedy", "url": "https://myanimelist.net/anime/genre/4/Comedy"}, {"mal_id": 27, "type": "anime", "name": "Shounen", "url": "https://myanimelist.net/anime/genre/27/Shounen"}], "opening_themes": ["\"Mission! Ken Kou Dai Ichi (\u30df\u30c3\u30b7\u30e7\u30f3\uff01\u5065\u30fb\u5eb7\u30fb\u7b2c\u30fb\u30a4\u30c1)\" by Sekkekkyuu (Kana Hanazawa), Hakkekkyuu (Tomoaki Maeno), Killer T Saibou (Daisuke Ono), Macrophage (Kikuko Inoue)"], "ending_themes": ["\"CheerS\" by ClariS"]}