{"request_hash": "request:anime:2d375dbc8d6b840bb7175d728903e1eefacaf0dd", "request_cached": true, "request_cache_expiry": 26232, "mal_id": 38027, "url": "https://myanimelist.net/anime/38027/Free__Dive_to_the_Future_Episode_0", "image_url": "https://cdn.myanimelist.net/images/anime/1386/93218.jpg", "trailer_url": "https://www.youtube.com/embed/VibZMSzc3pg?enablejsapi=1&wmode=opaque&autoplay=1", "title": "Free!: Dive to the Future Episode 0", "title_english": null, "title_japanese": "Free!-Dive to the Future- \u7b2c0\u8a71", "title_synonyms": [], "type": "Special", "source": "Original", "episodes": 1, "status": "Finished Airing", "airing": false, "aired": {"from": "2018-06-23T00:00:00+00:00", "to": null, "prop": {"from": {"day": 23, "month": 6, "year": 2018}, "to": {"day": null, "month": null, "year": null}}, "string": "Jun 23, 2018"}, "duration": "23 min", "rating": "PG-13 - Teens 13 or older", "score": 7.47, "scored_by": 3843, "rank": 1687, "popularity": 4814, "members": 10258, "favorites": 5, "synopsis": "Episode 0 of Free!: Dive to the Future was shown at a special Free! event. Episode 1 also pre-aired during this same event. Episode 0 will eventually be included in the BD/DVD release of Free!: Dive to the Future.", "background": null, "premiered": null, "broadcast": null, "related": {"Prequel": [{"mal_id": 35198, "type": "anime", "name": "Free!: Take Your Marks", "url": "https://myanimelist.net/anime/35198/Free__Take_Your_Marks"}], "Sequel": [{"mal_id": 36704, "type": "anime", "name": "Free!: Dive to the Future", "url": "https://myanimelist.net/anime/36704/Free__Dive_to_the_Future"}]}, "producers": [], "licensors": [], "studios": [{"mal_id": 2, "type": "anime", "name": "Kyoto Animation", "url": "https://myanimelist.net/anime/producer/2/Kyoto_Animation"}], "genres": [{"mal_id": 23, "type": "anime", "name": "School", "url": "https://myanimelist.net/anime/genre/23/School"}, {"mal_id": 36, "type": "anime", "name": "Slice of Life", "url": "https://myanimelist.net/anime/genre/36/Slice_of_Life"}, {"mal_id": 30, "type": "anime", "name": "Sports", "url": "https://myanimelist.net/anime/genre/30/Sports"}], "opening_themes": ["\"Heading to Over\" by OLDCODEX"], "ending_themes": ["\"Gold Evolution\" by STYLE FIVE"]}