{"request_hash": "request:anime:1666f0262e7df05f67943e485e6d5813c53334c5", "request_cached": true, "request_cache_expiry": 86400, "mal_id": 37144, "url": "https://myanimelist.net/anime/37144/Nikuiyo_Galbi-kun__Kemuri_ga_Me_ni_Shimiru", "image_url": "https://cdn.myanimelist.net/images/anime/1489/90148.jpg", "trailer_url": null, "title": "Nikuiyo! Galbi-kun: Kemuri ga Me ni Shimiru", "title_english": null, "title_japanese": "\u30cb\u30af\u3044\u3088\u3063\uff01\u30ab\u30eb\u30d3\u304f\u3093\uff5e\u7159\u304c\u76ee\u306b\u3057\u307f\u308b\uff5e", "title_synonyms": [], "type": "ONA", "source": "Original", "episodes": 5, "status": "Finished Airing", "airing": false, "aired": {"from": "2018-01-19T00:00:00+00:00", "to": "2018-05-17T00:00:00+00:00", "prop": {"from": {"day": 19, "month": 1, "year": 2018}, "to": {"day": 17, "month": 5, "year": 2018}}, "string": "Jan 19, 2018 to May 17, 2018"}, "duration": "2 min per ep", "rating": "G - All Ages", "score": null, "scored_by": null, "rank": 11052, "popularity": 15129, "members": 181, "favorites": 0, "synopsis": "A short gag anime about yakiniku meat on a grill. It primarily focuses on Galbi-kun (beef short rib) who admires a higher cut of meat and tries to change his demeanor to be more refined.", "background": null, "premiered": null, "broadcast": null, "related": {}, "producers": [], "licensors": [], "studios": [{"mal_id": 1133, "type": "anime", "name": "dwarf", "url": "https://myanimelist.net/anime/producer/1133/dwarf"}], "genres": [{"mal_id": 4, "type": "anime", "name": "Comedy", "url": "https://myanimelist.net/anime/genre/4/Comedy"}], "opening_themes": [], "ending_themes": []}