{"request_hash": "request:anime:10143572f023291f51a45c41e68e829b88443287", "request_cached": true, "request_cache_expiry": 26763, "mal_id": 17353, "url": "https://myanimelist.net/anime/17353/Tenpou_Suikoden_Neo", "image_url": "https://cdn.myanimelist.net/images/anime/2/46523.jpg", "trailer_url": null, "title": "Tenpou Suikoden Neo", "title_english": null, "title_japanese": "\u5929\u4fdd\u6c34\u6ef8\u4f1dNEO", "title_synonyms": [], "type": "TV", "source": "Unknown", "episodes": 5, "status": "Finished Airing", "airing": false, "aired": {"from": "2013-02-28T00:00:00+00:00", "to": "2013-03-28T00:00:00+00:00", "prop": {"from": {"day": 28, "month": 2, "year": 2013}, "to": {"day": 28, "month": 3, "year": 2013}}, "string": "Feb 28, 2013 to Mar 28, 2013"}, "duration": "2 min per ep", "rating": "PG-13 - Teens 13 or older", "score": 5.22, "scored_by": 165, "rank": 10235, "popularity": 10686, "members": 870, "favorites": 1, "synopsis": "The anime is based off an old Japanese story, which in turn was inspired by the classic Chinese novel Suikoden (Water Margin). In the original story, a large band of outlaws are given amnesty by the government to fight foreign forces and rebels. The Tenpou Suidoken version relocates the story to the Chiba Prefecture town of Tonosho, and it revolves around the chivalrous battles of Sasagawa no Shigezou and Iioka Sukegorou. (Source: ANN)", "background": null, "premiered": "Winter 2013", "broadcast": "Unknown", "related": {}, "producers": [], "licensors": [], "studios": [{"mal_id": 432, "type": "anime", "name": "Kachidoki Studio", "url": "https://myanimelist.net/anime/producer/432/Kachidoki_Studio"}], "genres": [{"mal_id": 13, "type": "anime", "name": "Historical", "url": "https://myanimelist.net/anime/genre/13/Historical"}], "opening_themes": [], "ending_themes": ["\"ADABANA\" by Naoki Sagawa featuring JOE (Psychic Lover) (\u72ed\u5ddd\u5c1a\u7d00 featuring JOE\uff08\u30b5\u30a4\u30ad\u30c3\u30af\u30e9\u30d0\u30fc\uff09)"]}