{"request_hash": "request:anime:87d93ed18d7b2eff36963b55579ad6eb30b56a7c", "request_cached": true, "request_cache_expiry": 86400, "mal_id": 30777, "url": "https://myanimelist.net/anime/30777/Kaijuu_Sakaba_Kanpai", "image_url": "https://cdn.myanimelist.net/images/anime/8/74081.jpg", "trailer_url": "https://www.youtube.com/embed/aup7FplHAcc?enablejsapi=1&wmode=opaque&autoplay=1", "title": "Kaijuu Sakaba Kanpai!", "title_english": null, "title_japanese": "\u602a\u7363\u9152\u5834\u30ab\u30f3\u30d1\u30fc\u30a4!", "title_synonyms": [], "type": "TV", "source": "Original", "episodes": 13, "status": "Finished Airing", "airing": false, "aired": {"from": "2015-07-07T00:00:00+00:00", "to": "2015-09-29T00:00:00+00:00", "prop": {"from": {"day": 7, "month": 7, "year": 2015}, "to": {"day": 29, "month": 9, "year": 2015}}, "string": "Jul 7, 2015 to Sep 29, 2015"}, "duration": "3 min per ep", "rating": "PG - Children", "score": null, "scored_by": null, "rank": 14733, "popularity": 12187, "members": 473, "favorites": 0, "synopsis": "Kaijuu Sakaba is a real tavern where kaijuu costumes from the Ultraman franchise are on display. Events are held where people can dine with the actors dressed in the kaijuu costumes. In honor of Kaijuu Sakaba's grand re-opening in Kawasaki and opening of a second tavern in Osaka this anime was made to focus on the kaijuu working at a tavern and the tribulations that come with it.", "background": null, "premiered": "Summer 2015", "broadcast": "Tuesdays at 21:55 (JST)", "related": {"Alternative version": [{"mal_id": 32143, "type": "anime", "name": "Peeping Life x Kaijuu Sakaba Kaiji: Kaijuu-tachi ga Iru Tokoro", "url": "https://myanimelist.net/anime/32143/Peeping_Life_x_Kaijuu_Sakaba_Kaiji__Kaijuu-tachi_ga_Iru_Tokoro"}], "Sequel": [{"mal_id": 32197, "type": "anime", "name": "Kaijuu Sakaba Kanpai! Specials", "url": "https://myanimelist.net/anime/32197/Kaijuu_Sakaba_Kanpai_Specials"}], "Other": [{"mal_id": 34872, "type": "anime", "name": "Tapuri Card x Kaijuu Sakaba Kanpai: Kanegon no Shuchou", "url": "https://myanimelist.net/anime/34872/Tapuri_Card_x_Kaijuu_Sakaba_Kanpai__Kanegon_no_Shuchou"}]}, "producers": [], "licensors": [], "studios": [{"mal_id": 276, "type": "anime", "name": "DLE", "url": "https://myanimelist.net/anime/producer/276/DLE"}], "genres": [{"mal_id": 4, "type": "anime", "name": "Comedy", "url": "https://myanimelist.net/anime/genre/4/Comedy"}, {"mal_id": 37, "type": "anime", "name": "Supernatural", "url": "https://myanimelist.net/anime/genre/37/Supernatural"}], "opening_themes": [], "ending_themes": []}