{"request_hash": "request:anime:8d0b21cdf217b989958894a893482b44b1b608a1", "request_cached": true, "request_cache_expiry": 86400, "mal_id": 30770, "url": "https://myanimelist.net/anime/30770/Maid-san_to_Boin_Damashii", "image_url": "https://cdn.myanimelist.net/images/anime/1184/104289.jpg", "trailer_url": null, "title": "Maid-san to Boin Damashii", "title_english": null, "title_japanese": "\u30e1\u30a4\u30c9\u3055\u3093\u3068\u30dc\u30a4\u30f3\u9b42", "title_synonyms": [], "type": "OVA", "source": "Visual novel", "episodes": 2, "status": "Finished Airing", "airing": false, "aired": {"from": "2015-07-03T00:00:00+00:00", "to": "2015-08-07T00:00:00+00:00", "prop": {"from": {"day": 3, "month": 7, "year": 2015}, "to": {"day": 7, "month": 8, "year": 2015}}, "string": "Jul 3, 2015 to Aug 7, 2015"}, "duration": "16 min per ep", "rating": "Rx - Hentai", "score": 5.62, "scored_by": 1006, "rank": null, "popularity": 7246, "members": 3684, "favorites": 9, "synopsis": "The head maid of a rich household wants to retire and choose someone else to replace her. Before she goes however, she decides to give her young master a farewell gift in the form of a hot sex session, followed by interviewing new potential maid recruits with another sex session. Can't complain.", "background": null, "premiered": null, "broadcast": null, "related": {"Adaptation": [{"mal_id": 69367, "type": "manga", "name": "Maid-san to Boin Damashii", "url": "https://myanimelist.net/manga/69367/Maid-san_to_Boin_Damashii"}]}, "producers": [{"mal_id": 319, "type": "anime", "name": "MS Pictures", "url": "https://myanimelist.net/anime/producer/319/MS_Pictures"}], "licensors": [], "studios": [], "genres": [{"mal_id": 35, "type": "anime", "name": "Harem", "url": "https://myanimelist.net/anime/genre/35/Harem"}, {"mal_id": 12, "type": "anime", "name": "Hentai", "url": "https://myanimelist.net/anime/genre/12/Hentai"}], "opening_themes": [], "ending_themes": []}