{"rating": "PG - Children", "request_cached": true, "favorites": 0, "aired": {"to": "2002-03-30T00:00:00+00:00", "from": "1999-04-05T00:00:00+00:00", "string": "Apr 5, 1999 to Mar 30, 2002", "prop": {"to": {"year": 2002, "day": 30, "month": 3}, "from": {"year": 1999, "day": 5, "month": 4}}}, "rank": 12871, "episodes": 80, "studios": [], "ending_themes": [], "duration": "1 min per ep", "genres": [{"mal_id": 15, "url": "https://myanimelist.net/anime/genre/15/Kids", "type": "anime", "name": "Kids"}], "request_hash": "request:anime:5df661f951acc19c873ea23b3b2cd6e0c1de4a9d", "title": "Yancharu Moncha", "source": "Unknown", "score": null, "type": "TV", "scored_by": null, "status": "Finished Airing", "title_japanese": "\u3084\u3093\u3061\u3083\u308b\u30e2\u30f3\u3061\u3083", "background": null, "title_english": null, "mal_id": 30116, "producers": [{"mal_id": 111, "url": "https://myanimelist.net/anime/producer/111/NHK", "type": "anime", "name": "NHK"}], "related": {}, "members": 151, "opening_themes": [], "title_synonyms": ["Yancharumon Cha", "Yancharumoncha", "Yancharumon Tea"], "airing": false, "request_cache_expiry": 85140, "broadcast": "Unknown", "licensors": [], "url": "https://myanimelist.net/anime/30116/Yancharu_Moncha", "popularity": 15666, "premiered": "Spring 1999", "synopsis": "An NHK toddler's anime following a green tea monkey and his mischief.", "image_url": "https://cdn.myanimelist.net/images/anime/13/72124.jpg", "trailer_url": null}