{"request_hash": "request:anime:6227bf908e84851b2689915ecf8bae164b6b1d47", "request_cached": true, "request_cache_expiry": 86400, "mal_id": 35624, "url": "https://myanimelist.net/anime/35624/Neko_ga_Kureta_Marui_Shiawase", "image_url": "https://cdn.myanimelist.net/images/anime/10/85878.jpg", "trailer_url": null, "title": "Neko ga Kureta Marui Shiawase", "title_english": null, "title_japanese": "\u732b\u304c\u304f\u308c\u305f\u307e\u3041\u308b\u3044\u3057\u3042\u308f\u305b", "title_synonyms": [], "type": "ONA", "source": "Original", "episodes": 5, "status": "Finished Airing", "airing": false, "aired": {"from": "2017-05-22T00:00:00+00:00", "to": "2018-03-23T00:00:00+00:00", "prop": {"from": {"day": 22, "month": 5, "year": 2017}, "to": {"day": 23, "month": 3, "year": 2018}}, "string": "May 22, 2017 to Mar 23, 2018"}, "duration": "53 sec per ep", "rating": "G - All Ages", "score": 6.2, "scored_by": 184, "rank": 7336, "popularity": 10530, "members": 935, "favorites": 0, "synopsis": "Protagonist Mari Hirakura joined the workforce almost 10 years ago. Even though she talks to her friends about things like jobs, marriage, age, and family, she still feels like everyone's troubles can be varied and complicated. She does her best every day but still wonders if she is okay the way she is. (Source: ANN)", "background": null, "premiered": null, "broadcast": null, "related": {"Character": [{"mal_id": 38058, "type": "anime", "name": "Oi-san to 40 no Monogatari", "url": "https://myanimelist.net/anime/38058/Oi-san_to_40_no_Monogatari"}]}, "producers": [], "licensors": [], "studios": [{"mal_id": 1687, "type": "anime", "name": "Yokohama Animation Lab", "url": "https://myanimelist.net/anime/producer/1687/Yokohama_Animation_Lab"}], "genres": [{"mal_id": 36, "type": "anime", "name": "Slice of Life", "url": "https://myanimelist.net/anime/genre/36/Slice_of_Life"}, {"mal_id": 4, "type": "anime", "name": "Comedy", "url": "https://myanimelist.net/anime/genre/4/Comedy"}], "opening_themes": [], "ending_themes": []}