{"request_hash": "request:anime:f67152daaa6c679ac0d9a2ffd2fc106545b9e9fd", "request_cached": true, "request_cache_expiry": 39189, "mal_id": 34389, "url": "https://myanimelist.net/anime/34389/Koro-sensei_Quest", "image_url": "https://cdn.myanimelist.net/images/anime/10/83452.jpg", "trailer_url": "https://www.youtube.com/embed/PeqLip6Wlbs?enablejsapi=1&wmode=opaque&autoplay=1", "title": "Koro-sensei Quest!", "title_english": "Koro Sensei Quest!", "title_japanese": "\u6bba\u305b\u3093\u305b\u30fcQ[\u30af\u30a8\u30b9\u30c8]!", "title_synonyms": ["Koro Teacher Quest 2016"], "type": "ONA", "source": "Manga", "episodes": 12, "status": "Finished Airing", "airing": false, "aired": {"from": "2016-12-23T00:00:00+00:00", "to": "2017-03-10T00:00:00+00:00", "prop": {"from": {"day": 23, "month": 12, "year": 2016}, "to": {"day": 10, "month": 3, "year": 2017}}, "string": "Dec 23, 2016 to Mar 10, 2017"}, "duration": "10 min per ep", "rating": "PG-13 - Teens 13 or older", "score": 7.12, "scored_by": 16566, "rank": 3121, "popularity": 2695, "members": 35272, "favorites": 47, "synopsis": "One day, class 3-E of Kunugigaoka Magic School receives a special mission: to kill their homeroom teacher, the Demon King Koro-sensei. To increase their chances of succeeding, the class searches for the three most powerful warriors\u2014Karma Akabane, Itona Horibe, and Ritsu\u2014who later join their company. Even with their help, accomplishing the mission becomes an insurmountable task as they are not the only ones after the Demon King's life. Koro-sensei Quest! tells the comedic adventures of Nagisa Shiota and class 3-E as chibi magical students. Trained by none other than their very target, the students encounter challenging, yet hilarious situations all through the perilous mission of defeating the Demon King. [Written by MAL Rewrite]", "background": null, "premiered": null, "broadcast": null, "related": {"Adaptation": [{"mal_id": 93353, "type": "manga", "name": "Koro-sensei Q!", "url": "https://myanimelist.net/manga/93353/Koro-sensei_Q"}], "Alternative version": [{"mal_id": 33511, "type": "anime", "name": "Koro-sensei Q!", "url": "https://myanimelist.net/anime/33511/Koro-sensei_Q"}]}, "producers": [], "licensors": [{"mal_id": 102, "type": "anime", "name": "Funimation", "url": "https://myanimelist.net/anime/producer/102/Funimation"}], "studios": [{"mal_id": 456, "type": "anime", "name": "Lerche", "url": "https://myanimelist.net/anime/producer/456/Lerche"}], "genres": [{"mal_id": 4, "type": "anime", "name": "Comedy", "url": "https://myanimelist.net/anime/genre/4/Comedy"}, {"mal_id": 16, "type": "anime", "name": "Magic", "url": "https://myanimelist.net/anime/genre/16/Magic"}, {"mal_id": 27, "type": "anime", "name": "Shounen", "url": "https://myanimelist.net/anime/genre/27/Shounen"}], "opening_themes": ["\"Re:QUEST!\" by Kaede Kayano (Aya Suzaki)"], "ending_themes": ["\"Seishun Satsubatsu-ron Remix (\u9752\u6625\u30b5\u30c4\u30d0\u30c4\u8ad6)\" by 3-nen E-gumi Utatan (3\u5e74E\u7d44\u3046\u305f\u62c5)"]}