{"request_hash": "request:anime:cd7a5ca0c896cafbbe49681a44c626a169bea401", "request_cached": true, "request_cache_expiry": 86400, "mal_id": 32707, "url": "https://myanimelist.net/anime/32707/Jewelpet__Attack_Chance", "image_url": "https://cdn.myanimelist.net/images/anime/11/78499.jpg", "trailer_url": null, "title": "Jewelpet: Attack Chance!?", "title_english": null, "title_japanese": "\u30b8\u30e5\u30a8\u30eb\u30da\u30c3\u30c8 \u3042\u305f\u3063\u304f\u3061\u3083\u3093\u3059!?", "title_synonyms": [], "type": "ONA", "source": "Original", "episodes": 3, "status": "Finished Airing", "airing": false, "aired": {"from": "2016-02-19T00:00:00+00:00", "to": "2016-05-30T00:00:00+00:00", "prop": {"from": {"day": 19, "month": 2, "year": 2016}, "to": {"day": 30, "month": 5, "year": 2016}}, "string": "Feb 19, 2016 to May 30, 2016"}, "duration": "4 min per ep", "rating": "PG - Children", "score": 5.74, "scored_by": 167, "rank": 8987, "popularity": 11104, "members": 734, "favorites": 1, "synopsis": null, "background": null, "premiered": null, "broadcast": null, "related": {"Alternative setting": [{"mal_id": 6008, "type": "anime", "name": "Jewelpet", "url": "https://myanimelist.net/anime/6008/Jewelpet"}, {"mal_id": 8217, "type": "anime", "name": "Jewelpet Twinkle\u2606", "url": "https://myanimelist.net/anime/8217/Jewelpet_Twinkle\u2606"}, {"mal_id": 10359, "type": "anime", "name": "Jewelpet Sunshine", "url": "https://myanimelist.net/anime/10359/Jewelpet_Sunshine"}, {"mal_id": 12963, "type": "anime", "name": "Jewelpet Kira\u2606Deco!", "url": "https://myanimelist.net/anime/12963/Jewelpet_Kira\u2606Deco"}, {"mal_id": 17497, "type": "anime", "name": "Jewelpet Happiness", "url": "https://myanimelist.net/anime/17497/Jewelpet_Happiness"}, {"mal_id": 22693, "type": "anime", "name": "Lady Jewelpet", "url": "https://myanimelist.net/anime/22693/Lady_Jewelpet"}, {"mal_id": 30030, "type": "anime", "name": "Jewelpet Magical Change", "url": "https://myanimelist.net/anime/30030/Jewelpet_Magical_Change"}]}, "producers": [{"mal_id": 48, "type": "anime", "name": "AIC", "url": "https://myanimelist.net/anime/producer/48/AIC"}, {"mal_id": 150, "type": "anime", "name": "Sanrio", "url": "https://myanimelist.net/anime/producer/150/Sanrio"}], "licensors": [], "studios": [], "genres": [{"mal_id": 4, "type": "anime", "name": "Comedy", "url": "https://myanimelist.net/anime/genre/4/Comedy"}, {"mal_id": 16, "type": "anime", "name": "Magic", "url": "https://myanimelist.net/anime/genre/16/Magic"}, {"mal_id": 10, "type": "anime", "name": "Fantasy", "url": "https://myanimelist.net/anime/genre/10/Fantasy"}, {"mal_id": 25, "type": "anime", "name": "Shoujo", "url": "https://myanimelist.net/anime/genre/25/Shoujo"}], "opening_themes": [], "ending_themes": []}